taskgen/__init__.py
taskgen/config.py
taskgen/converters.py
taskgen/functions.py
taskgen/html.py
taskgen/main.py
taskgen/moodle.py
taskgen/stats.py
taskgen/tex.py
taskgen/variable_types.py
taskgen-0.3.8.1.dist-info/METADATA
taskgen-0.3.8.1.dist-info/WHEEL
taskgen-0.3.8.1.dist-info/top_level.txt
taskgen-0.3.8.1.dist-info/RECORD
