Metadata-Version: 2.1
Name: taskgen
Version: 0.3.8.1
Summary: Ядро генератора банка задач на базе MiKTeX и Jupyter Notebook
Home-page: https://github.com/artyom-zolotarevskiy/taskgen-core
Author: Артём Золотаревский
Author-email: artyom@zolotarevskiy.ru
Project-URL: Bug Tracker, https://github.com/artyom-zolotarevskiy/taskgen-core/issues
Classifier: Programming Language :: Python :: 3
Classifier: Operating System :: OS Independent
